srvwrapper.py
srvwrapper-1.5.data/data/Scripts/ServiceWrapper.exe
srvwrapper-1.5.dist-info/LICENSE
srvwrapper-1.5.dist-info/METADATA
srvwrapper-1.5.dist-info/WHEEL
srvwrapper-1.5.dist-info/entry_points.txt
srvwrapper-1.5.dist-info/top_level.txt
srvwrapper-1.5.dist-info/RECORD
