Metadata-Version: 2.1
Name: srvwrapper
Version: 1.5
Summary: srvwrapper wraps any applications to run as Windows Service
Home-page: https://github.com/koho/srvwrapper
Author: Gerhard Tan
Author-email: gerhard.gh.ta@gmail.com
License: UNKNOWN
Platform: UNKNOWN
